README.rst
demo_sloq.py
setup.py
sloq.py
sloq.egg-info/PKG-INFO
sloq.egg-info/SOURCES.txt
sloq.egg-info/dependency_links.txt
sloq.egg-info/top_level.txt