Metadata-Version: 1.1
Name: sloq
Version: 0.2
Summary: Rate-limited Queue
Home-page: https://github.com/duedil-ltd/python-sloq
Author: Paul Scott, Duedil Limited
Author-email: paul@duedil.com
License: MIT
Download-URL: https://github.com/duedil-ltd/python-sloq/tarball/0.2
Keywords: queue,rate,limit,slow,token,bucket
Platform: UNKNOWN
